Metadata-Version: 1.0
Name: JGB-distributions
Version: 1.3
Summary: JGB_distributions is a Python library for dealing with Gaussian (normal) and Binomial Probability distributions.
Home-page: UNKNOWN
Author: Mohamed Youssef
Author-email: m.youssef315@yahoo.com
License: UNKNOWN
Platform: UNKNOWN
